[
    {
        "datetime": 201501240215,
        "address": "臺南市南區明興路1087巷明興路(口)及灣裡路211巷口南側(附近)",
        "death": 1,
        "injury": 0,
        "vehicles": [
            "普通重型-機車"
        ]
    },
    {
        "datetime": 201501240435,
        "address": "彰化縣伸港鄉中興路2段",
        "death": 1,
        "injury": 0,
        "vehicles": [
            "自用-小客車"
        ]
    },
    {
        "datetime": 201501240529,
        "address": "新北市雙溪區臺2丙線道路前0公尺數臺2丙線道19公里800公尺處西向快車道車道19.8公里",
        "death": 1,
        "injury": 0,
        "vehicles": [
            "營業用-小貨車",
            "行人-人"
        ]
    },
    {
        "datetime": 201501240758,
        "address": "高雄市路竹區北嶺六路民治路(口)",
        "death": 1,
        "injury": 0,
        "vehicles": [
            "普通輕型-機車",
            "自用-小客車"
        ]
    },
    {
        "datetime": 201501240929,
        "address": "桃園市桃園區大興西路三段吉祥路(M10401822)(附近)",
        "death": 1,
        "injury": 0,
        "vehicles": [
            "自用-小客車",
            "普通重型-機車"
        ]
    },
    {
        "datetime": 201501241142,
        "address": "嘉義市東區博愛路1段(果菜市場內)",
        "death": 1,
        "injury": 0,
        "vehicles": [
            "普通重型-機車",
            "自用-大貨車"
        ]
    },
    {
        "datetime": 201501241219,
        "address": "臺南市鹽水區水秀里華新高幹43號前叉路口(&#21452;鶴公司旁)(附近)南80線1公里500公尺處北向路口車道",
        "death": 1,
        "injury": 0,
        "vehicles": [
            "普通重型-機車",
            "自用-小貨車"
        ]
    },
    {
        "datetime": 201501241524,
        "address": "南投縣名間鄉名山路50-3號旁(附近)",
        "death": 1,
        "injury": 0,
        "vehicles": [
            "普通重型-機車",
            "營業用-大貨車"
        ]
    },
    {
        "datetime": 201501242350,
        "address": "高雄市湖內區忠孝街113巷口",
        "death": 1,
        "injury": 1,
        "vehicles": [
            "自用-小貨車",
            "普通重型-機車"
        ]
    }
]