[
    {
        "datetime": 201502221010,
        "address": "苗栗縣南庄鄉南江村苗124線32.5K處(附近)",
        "death": 1,
        "injury": 0,
        "vehicles": [
            "自用-小客車"
        ]
    },
    {
        "datetime": 201502221105,
        "address": "雲林縣東勢鄉新坤村158甲線3公里600公尺處東向內側車道",
        "death": 1,
        "injury": 0,
        "vehicles": [
            "自用-小貨車",
            "普通重型-機車"
        ]
    },
    {
        "datetime": 201502221134,
        "address": "花蓮縣壽豐鄉中華路二段92巷-志學所轄區(附近)台9線219公里500公尺處南向外側車道",
        "death": 1,
        "injury": 1,
        "vehicles": [
            "自用-小貨車",
            "普通重型-機車",
            "自用-小客車",
            "普通重型-機車"
        ]
    },
    {
        "datetime": 201502222345,
        "address": "高雄市仁武區鳳仁路106號前",
        "death": 1,
        "injury": 0,
        "vehicles": [
            "自用-小客車",
            "普通重型-機車"
        ]
    }
]