[
    {
        "datetime": 20150327,
        "address": "臺南市善化區什乃里125號(附近)",
        "death": 1,
        "injury": 0,
        "vehicles": [
            "普通重型-機車",
            "自用-小貨車"
        ]
    },
    {
        "datetime": 20150327,
        "address": "新竹市東區千甲里國道一號93公里200公尺處北向外側路肩車道",
        "death": 1,
        "injury": 0,
        "vehicles": [
            "營業用-全聯結車"
        ]
    },
    {
        "datetime": 20150327,
        "address": "嘉義縣太保市南新里中山路一段62附1號159線13公里530公尺處西向外側車道",
        "death": 1,
        "injury": 1,
        "vehicles": [
            "營業用-曳引車",
            "普通重型-機車",
            "普通重型-機車"
        ]
    },
    {
        "datetime": 20150327,
        "address": "新竹縣新豐鄉國道一號86公里900公尺處南向內側車道",
        "death": 1,
        "injury": 3,
        "vehicles": [
            "營業用-半聯結車",
            "自用-小客車",
            "自用-小客車",
            "營業用-小貨車",
            "自用-小貨車",
            "自用-小貨車",
            "自用-小貨車"
        ]
    },
    {
        "datetime": 20150327,
        "address": "屏東縣佳冬鄉六根村佳和路216號前（台17線265.1公里處 南向）(附近)台17線265公里100公尺處南向內側車道",
        "death": 1,
        "injury": 2,
        "vehicles": [
            "營業用-曳引車",
            "營業用-大貨車",
            "普通重型-機車",
            "營業用-大貨車"
        ]
    },
    {
        "datetime": 20150327,
        "address": "高雄市湖內區中山路一段民生街口(口)",
        "death": 1,
        "injury": 0,
        "vehicles": [
            "自用-小客車",
            "普通重型-機車"
        ]
    }
]