[
    {
        "datetime": 20150607,
        "address": "苗栗縣苑裡鎮國道三號154公里700公尺處北向中線車道",
        "death": 1,
        "injury": 2,
        "vehicles": [
            "自用-小客車",
            "自用-小貨車",
            "租賃車-小客車",
            "自用-小客車",
            "其他人-人",
            "其他人-人",
            "自用-小客車"
        ]
    },
    {
        "datetime": 20150607,
        "address": "高雄市前鎮區國道一號372公里300公尺處南向交流道車道",
        "death": 1,
        "injury": 0,
        "vehicles": [
            "自用-小客車"
        ]
    },
    {
        "datetime": 20150607,
        "address": "臺南市永康區大同街與大同街623巷路口(附近)",
        "death": 1,
        "injury": 0,
        "vehicles": [
            "普通輕型-機車"
        ]
    },
    {
        "datetime": 20150607,
        "address": "臺中市南屯區新生里環中路永春路(口)",
        "death": 1,
        "injury": 0,
        "vehicles": [
            "普通重型-機車",
            "自用-小客車"
        ]
    },
    {
        "datetime": 20150607,
        "address": "高雄市仁武區鳳仁路中正路口(口)",
        "death": 1,
        "injury": 2,
        "vehicles": [
            "自用-小客車",
            "普通重型-機車",
            "普通重型-機車",
            "普通重型-機車",
            "普通輕型-機車"
        ]
    }
]